dbtlabs_vortex/__init__.py
dbtlabs_vortex/py.typed
dbtlabs_vortex/common/__init__.py
dbtlabs_vortex/common/exceptions.py
dbtlabs_vortex/common/exceptions.pyi
dbtlabs_vortex/producer/__init__.py
dbtlabs_vortex/producer/client.py
dbtlabs_vortex/producer/client.pyi
dbtlabs_vortex/producer/ddtrace.py
dbtlabs_vortex/producer/ddtrace.pyi
dbtlabs_vortex/producer/tests/test_client.py
dbtlabs_vortex/producer/tests/test_ddtrace.py
dbtlabs_vortex-0.2.0.dist-info/METADATA
dbtlabs_vortex-0.2.0.dist-info/WHEEL
dbtlabs_vortex-0.2.0.dist-info/top_level.txt
dbtlabs_vortex-0.2.0.dist-info/RECORD
