Metadata-Version: 2.4
Name: dbtlabs-vortex
Version: 0.2.0
Summary: Python client for Vortex
Author-email: Connor McArthur <connor@dbtlabs.com>, Zach Brown <zach.brown@dbtlabs.com>
Project-URL: Homepage, https://github.com/dbt-labs/vortex
Project-URL: Bug Tracker, https://dbtlabs.atlassian.net/jira/software/c/projects/VX/issues
Classifier: Intended Audience :: Developers
Classifier: Programming Language :: Python :: 3
Classifier: Programming Language :: Python :: 3.8
Classifier: Programming Language :: Python :: 3.9
Classifier: Programming Language :: Python :: 3.10
Classifier: Programming Language :: Python :: 3.11
Classifier: Programming Language :: Python :: 3.12
Classifier: Programming Language :: Python :: 3.13
Requires-Python: >=3.8
Requires-Dist: dbt-protos>=1.0.315
Requires-Dist: pydantic>=1
Requires-Dist: requests>=2.32.3
Requires-Dist: uuid>=1.30
Provides-Extra: dev
Requires-Dist: types-protobuf; extra == "dev"
Requires-Dist: types-requests; extra == "dev"
Requires-Dist: pytest>=7.4.0; extra == "dev"
Requires-Dist: pytest-cov>=4.1.0; extra == "dev"
Requires-Dist: black>=23.7.0; extra == "dev"
Requires-Dist: isort>=5.12.0; extra == "dev"
Requires-Dist: mypy>=1.5.1; extra == "dev"
Requires-Dist: pylint>=2.17.5; extra == "dev"
Requires-Dist: ruff>=0.9.0; extra == "dev"
Provides-Extra: ddtrace
Requires-Dist: ddtrace<3,>=1; extra == "ddtrace"
